{
  "frame": 360,
  "timestamp": 1749851175.1088536,
  "detections": [
    {
      "class": "boat",
      "confidence": 0.5817041993141174,
      "center": {
        "x": 491,
        "y": 209
      },
      "bbox": {
        "x1": 373,
        "y1": 63,
        "x2": 610,
        "y2": 356
      },
      "position_estimate": {
        "x": 171,
        "y": -31,
        "z": 0.49
      }
    },
    {
      "class": "person",
      "confidence": 0.5042067170143127,
      "center": {
        "x": 438,
        "y": 309
      },
      "bbox": {
        "x1": 425,
        "y1": 299,
        "x2": 451,
        "y2": 319
      },
      "position_estimate": {
        "x": 118,
        "y": 69,
        "z": 9.6
      }
    }
  ]
}