{
  "frame": 361,
  "timestamp": 1749851175.4442186,
  "detections": [
    {
      "class": "boat",
      "confidence": 0.8299383521080017,
      "center": {
        "x": 524,
        "y": 185
      },
      "bbox": {
        "x1": 411,
        "y1": 34,
        "x2": 638,
        "y2": 336
      },
      "position_estimate": {
        "x": 204,
        "y": -55,
        "z": 0.48
      }
    },
    {
      "class": "person",
      "confidence": 0.6064243316650391,
      "center": {
        "x": 473,
        "y": 287
      },
      "bbox": {
        "x1": 461,
        "y1": 276,
        "x2": 486,
        "y2": 299
      },
      "position_estimate": {
        "x": 153,
        "y": 47,
        "z": 8.35
      }
    }
  ]
}